generator/__init__.py
generator/controller.py
generator/dto.py
generator/entity.py
generator/repository.py
generator/service.py
spring-boot-crud-generator/__init__.py
spring-boot-crud-generator/crud.py
springcrud/__init__.py
springcrud/crud.py
springcrud/generator/__init__.py
springcrud/generator/controller.py
springcrud/generator/dto.py
springcrud/generator/entity.py
springcrud/generator/repository.py
springcrud/generator/service.py
springcrud/utils/__init__.py
springcrud/utils/file.py
springcrud/utils/input.py
springcrud/utils/output.py
utils/__init__.py
utils/file.py
utils/input.py
utils/output.py
spring_boot_crud_generator-0.0.8.dist-info/METADATA
spring_boot_crud_generator-0.0.8.dist-info/WHEEL
spring_boot_crud_generator-0.0.8.dist-info/entry_points.txt
spring_boot_crud_generator-0.0.8.dist-info/top_level.txt
spring_boot_crud_generator-0.0.8.dist-info/RECORD
