Metadata-Version: 2.4
Name: spring-boot-crud-generator
Version: 0.0.8
Summary: Spring Boot CRUD 코드 생성기
Home-page: https://github.com/wonowonow/spring-boot-crud-generator
Author: wonow
Author-email: wonowdaily@gmail.com
Classifier: Programming Language :: Python :: 3
Classifier: Operating System :: OS Independent
Requires-Python: >=3.6
Dynamic: author
Dynamic: author-email
Dynamic: classifier
Dynamic: description
Dynamic: description-content-type
Dynamic: home-page
Dynamic: requires-python
Dynamic: summary
